pypixcode/__init__.py
pypixcode/builders/__init__.py
pypixcode/builders/pix.py
pypixcode/commons/__init__.py
pypixcode/commons/claculator.py
pypixcode/commons/qr_code.py
pypixcode-1.0.4.dist-info/METADATA
pypixcode-1.0.4.dist-info/WHEEL
pypixcode-1.0.4.dist-info/RECORD
