Metadata-Version: 2.1
Name: pypixcode
Version: 1.0.4
Summary: Este projeto é uma biblioteca Python para gerar codigo e qrcode do Pix. Ele fornece uma interface simples e intuitiva para criar, modificar e validar dados de Pix.
Keywords: packaging,pix,qrcode
Author: bruno.duarte
Author-email: brunomacielduarte32@gmail.com
Requires-Python: >=3.13,<4.0
Classifier: Programming Language :: Python :: 3
Classifier: Programming Language :: Python :: 3.13
Requires-Dist: crcmod (>=1.7,<2.0)
Requires-Dist: segno (>=1.6.1,<2.0.0)
Project-URL: Repository, https://github.com/brduarte/pypixcode
